{
  "pet_stats": {
    "hp_max_base": 100,
    "hp_max_per_level": 15,
    "atk_base": 5,
    "atk_per_level": 2,
    "exp_to_level": [0, 30, 80, 150, 250, 400, 600, 850, 1200, 1600],
    "max_level": 10,
    "stages": [
      {"min_level": 1, "name": "蛋", "emoji": "🥚", "size": 0.7},
      {"min_level": 3, "name": "幼崽", "emoji": "🐣", "size": 0.85},
      {"min_level": 5, "name": "成长期", "emoji": "🐥", "size": 1.0},
      {"min_level": 8, "name": "完全体", "emoji": "🦅", "size": 1.2}
    ]
  },
  "battle_system": {
    "type": "auto_turn_based",
    "tick_interval_ms": 1500,
    "win_rewards": {
      "exp_base": 10,
      "exp_per_danger_level": 5,
      "drop_chance_base": 0.5
    },
    "lose_consequences": {
      "hp_loss_percent": 50,
      "lose_items_chance": 0.3,
      "exp_loss": 0
    },
    "flee_chance": 0.3,
    "flee_rewards": {
      "exp_partial": 0.3
    }
  },
  "exploration_costs": {
    "hp_per_explore": "scene.hp_cost",
    "stamina_per_explore": 1,
    "stamina_regen_minutes": 30
  },
  "safety_mechanics": {
    "low_hp_warning": 30,
    "critical_hp_warning": 10,
    "auto_flee_threshold": 15,
    "no_ko_protection": true,
    "ko_recovery": "auto_revive_with_50_percent_hp_after_5_minutes"
  }
}